cloe_snowflake_feature_db_clone/__init__.py
cloe_snowflake_feature_db_clone/main.py
cloe_snowflake_feature_db_clone/models/__init__.py
cloe_snowflake_feature_db_clone/models/overwrite_config.py
cloe_snowflake_feature_db_clone/models/stage_overwrite.py
cloe_snowflake_feature_db_clone/py.typed
cloe_snowflake_feature_db_clone/templates/__init__.py
cloe_snowflake_feature_db_clone/templates/alter_stage.sql.j2
cloe_snowflake_feature_db_clone/templates/clone_database.sql.j2
cloe_snowflake_feature_db_clone/utils/__init__.py
cloe_snowflake_feature_db_clone/utils/create_functional_role_rewrites.py
cloe_snowflake_feature_db_clone/utils/prepare_clone.py
cloe_snowflake_feature_db_clone/utils/template_env.py
cloe_snowflake_feature_db_clone-1.0.2.dist-info/METADATA
cloe_snowflake_feature_db_clone-1.0.2.dist-info/WHEEL
cloe_snowflake_feature_db_clone-1.0.2.dist-info/entry_points.txt
cloe_snowflake_feature_db_clone-1.0.2.dist-info/RECORD
