Metadata-Version: 2.3
Name: cloe-snowflake-feature-db-clone
Version: 1.0.2
Summary: This Package automatically creates a clone of a target database in Snowflake to support easy feature driven development.
Home-page: https://initions.com/
Author: initions
Author-email: ICSMC_EXT_PYPIORG@accenture.com
License: MIT
Requires-Python: >=3.11,<3.12
Requires-Dist: cloe-metadata (>=2.2.4,<3.0.0)
Requires-Dist: cloe-snowflake-rbac (>=2.0.2,<3.0.0)
Requires-Dist: jinja2 (==3.1.2)
Requires-Dist: pydantic (>=2.5.3,<3.0.0)
Requires-Dist: typer[all] (>=0.9.0,<0.10.0)
